provisioner_shared/components/__init__.py
provisioner_shared/components/anchor/__init__.py
provisioner_shared/components/anchor/anchor_runner.py
provisioner_shared/components/anchor/playbooks/anchor_run.yaml
provisioner_shared/components/external/__init__.py
provisioner_shared/components/external/ansible_playbooks/Makefile
provisioner_shared/components/external/ansible_playbooks/__init__.py
provisioner_shared/components/external/ansible_playbooks/playbooks/apt_update_upgrade.yaml
provisioner_shared/components/external/ansible_playbooks/playbooks/common/shell_lib.sh
provisioner_shared/components/external/ansible_playbooks/playbooks/group_vars/all
provisioner_shared/components/external/ansible_playbooks/playbooks/reboot.yaml
provisioner_shared/components/external/ansible_playbooks/playbooks/roles/anchor/defaults/main.yaml
provisioner_shared/components/external/ansible_playbooks/playbooks/roles/anchor/files/anchor_run.sh
provisioner_shared/components/external/ansible_playbooks/playbooks/roles/anchor/files/shell_lib.sh
provisioner_shared/components/external/ansible_playbooks/playbooks/roles/anchor/tasks/main.yaml
provisioner_shared/components/external/ansible_playbooks/playbooks/roles/dhcp_static_ip/defaults/main.yaml
provisioner_shared/components/external/ansible_playbooks/playbooks/roles/dhcp_static_ip/files/add_dhcp_entry.sh
provisioner_shared/components/external/ansible_playbooks/playbooks/roles/dhcp_static_ip/files/shell_lib.sh
provisioner_shared/components/external/ansible_playbooks/playbooks/roles/dhcp_static_ip/tasks/main.yaml
provisioner_shared/components/external/ansible_playbooks/playbooks/roles/docker/defaults/main.yaml
provisioner_shared/components/external/ansible_playbooks/playbooks/roles/docker/files/docker_role.sh
provisioner_shared/components/external/ansible_playbooks/playbooks/roles/docker/files/shell_lib.sh
provisioner_shared/components/external/ansible_playbooks/playbooks/roles/docker/tasks/main.yaml
provisioner_shared-0.1.25.dist-info/METADATA
provisioner_shared-0.1.25.dist-info/WHEEL
provisioner_shared-0.1.25.dist-info/RECORD
