Metadata-Version: 2.3
Name: provisioner_shared
Version: 0.1.25
Summary: Shared package used by the provisioner runtime and plugins
Author: Zachi Nachshon
Author-email: zachi.nachshon@gmail.com
Requires-Python: >=3.11,<4.0
Classifier: Programming Language :: Python :: 3
Classifier: Programming Language :: Python :: 3.11
Classifier: Programming Language :: Python :: 3.12
Classifier: Programming Language :: Python :: 3.13
Requires-Dist: PyYAML (>=6.0,<7.0)
Requires-Dist: ansible-core (>=2.18.5,<3.0.0)
Requires-Dist: ansible-runner (>=2.4.1,<3.0.0)
Requires-Dist: click (>=8.1.8,<9.0.0)
Requires-Dist: inquirer (>=2.10,<4.0)
Requires-Dist: loguru (>=0.6,<0.8)
Requires-Dist: paramiko (>=3.5.1,<5.0.0)
Requires-Dist: passlib (>=1.7.4,<2.0.0)
Requires-Dist: python-hosts (>=1.0.3,<2.0.0)
Requires-Dist: python-libnmap (>=0.7.3,<0.8.0)
Requires-Dist: python3-nmap (>=1.5.4,<2.0.0)
Requires-Dist: requests (>=2.28.1,<3.0.0)
Requires-Dist: rich (>=12.5.1,<15.0.0)
